dx_utilities/__init__.py
dx_utilities/array_interface.py
dx_utilities/checks.py
dx_utilities/data_structures.py
dx_utilities/decorators.py
dx_utilities/exceptions.py
dx_utilities/integrals.py
dx_utilities/linear_algebra.py
dx_utilities/physical_constants.py
dx_utilities/pretty_print.py
dx_utilities/testing.py
dx_utilities/units.py
dx_utilities/vectors.py
dx_utilities/bin/__init__.py
dx_utilities/bin/parse_error_codes.py
dx_utilities/fields/__init__.py
dx_utilities/fields/base.py
dx_utilities/fields/fields.py
dx_utilities/fields/mixins.py
dx_utilities/geometry/__init__.py
dx_utilities/geometry/linear.py
dx_utilities/geometry/operations.py
dx_utilities/geometry/planar.py
dx_utilities/geometry/points.py
dx_utilities-1.0.2.dist-info/LICENSE
dx_utilities-1.0.2.dist-info/METADATA
dx_utilities-1.0.2.dist-info/WHEEL
dx_utilities-1.0.2.dist-info/top_level.txt
dx_utilities-1.0.2.dist-info/RECORD
